CHANGES.rst
CREDITS.rst
LICENSE.rst
MANIFEST.in
README.rst
setup.cfg
setup.py
lizard_connector/__init__.py
lizard_connector/callbacks.py
lizard_connector/connector.py
lizard_connector/exceptions.py
lizard_connector/jsdatetime.py
lizard_connector/parsers.py
lizard_connector/queries.py
lizard_connector.egg-info/PKG-INFO
lizard_connector.egg-info/SOURCES.txt
lizard_connector.egg-info/dependency_links.txt
lizard_connector.egg-info/entry_points.txt
lizard_connector.egg-info/not-zip-safe
lizard_connector.egg-info/requires.txt
lizard_connector.egg-info/top_level.txt