Metadata-Version: 2.1
Name: lizard-connector
Version: 0.7.3
Summary: A connector to connect to the Lizard-API with Python.
Home-page: http://demo.lizard.net
Author: Roel van den Berg
Author-email: roel.vandenberg@nelen-schuurmans.nl
License: GPL
Keywords: lizard,rest,interface,api
Platform: UNKNOWN
Classifier: Topic :: Software Development :: Libraries :: Application Frameworks
Provides-Extra: test
